AutoSphereExcel/AutoSphereExcel.py
AutoSphereExcel/__init__.py
autosphere_excel-1.0.3.dist-info/METADATA
autosphere_excel-1.0.3.dist-info/WHEEL
autosphere_excel-1.0.3.dist-info/top_level.txt
autosphere_excel-1.0.3.dist-info/RECORD
