Metadata-Version: 2.1
Name: autosphere-excel
Version: 1.0.3
Summary: Autosphere library for excel xlsx file format
Home-page: https://github.com/mercurialmindsrpa/autosphere-excel.git
Author: Abdul Mateen
Author-email: abdul.mateen@mercurialminds.com
License: UNKNOWN
Platform: UNKNOWN
Requires-Dist: openpyxl
Requires-Dist: xlsxwriter
